pelican_social-0.2.0.dist-info/DESCRIPTION.rst
pelican_social-0.2.0.dist-info/METADATA
pelican_social-0.2.0.dist-info/RECORD
pelican_social-0.2.0.dist-info/WHEEL
pelican_social-0.2.0.dist-info/metadata.json
pelican_social-0.2.0.dist-info/top_level.txt
social/__init__.py
social/plugin.py
social/tests.py
social/test-resources/facebook.rst
social/test-resources/github-issue.rst
social/test-resources/github-repository.rst
social/test-resources/github.rst
social/test-resources/google_plus.rst
social/test-resources/twitter.rst
